{
"type": "text_with_image",
  "title": {
  "text": "Title",
  "font_size": "14",
  "font_weight": "normal",
  "color": "black"
},
"subtitle": {
  "text": "Subtitle",
  "font_size": "12",
  "font_weight": "normal",
  "color": "gray"
},
"image": {
  "src":
  "https://i.imgur.com/KavRSSi.jpeg"
},
"height": 30,
"click_action": "dismiss"
}

{ 
"type": "text", 
"text": "Lorem ipsum dolor sit amet, consectetur adipiscing elit, sed do eiusmod tempor incididunt ut labore et dolore magna aliqua.", "font_size": "12", 
"font_weight": "normal", 
"color": "gray", 
"click_action": "present_popup", 
"click_action_data": { 
"data": [ 
{ 
"type": "text",
"text": "This is my popup!", 
"click_action": "dismiss" 
} 
] 
} 
}




